ronswanson
scripts
